simpletestpackage/__init__.py
simpletestpackage/add.py
simpletestpackage/hello.py
simpletestpackage/multiple.py
simpletestpackage/test.py
simpletestpackage-0.0.7.dist-info/METADATA
simpletestpackage-0.0.7.dist-info/WHEEL
simpletestpackage-0.0.7.dist-info/top_level.txt
simpletestpackage-0.0.7.dist-info/RECORD
